setup.py
ThreadDownloader2211.egg-info/PKG-INFO
ThreadDownloader2211.egg-info/SOURCES.txt
ThreadDownloader2211.egg-info/dependency_links.txt
ThreadDownloader2211.egg-info/requires.txt
ThreadDownloader2211.egg-info/top_level.txt
htmlprocessor/__init__.py
htmlprocessor/grabber.py
simplethread/__init__.py
simplethread/threadingbyfunction.py
simplethread/threadpool.py