Metadata-Version: 1.0
Name: ThreadDownloader2211
Version: 1.1.2
Summary: my first python distribution
Home-page: UNKNOWN
Author: UNKNOWN
Author-email: UNKNOWN
License: UNKNOWN
Platform: UNKNOWN
